Workbook
Name Slicer_ticket_priority: #N/A
Name Slicer_ticket_status: #N/A
Name Slicer_ticket_type: #N/A

Sheet _Static_Dashboard
B1: Support Tickets Dashboard

Sheet Dashboard
B1: Customer Support Performance & Satisfaction Dashboard
C13: Total Tickets | F13: AVG CSAT Rating | I13: AVG Resolution Time | L13: Closed Rate (%) | O13: Backlog Tickets | R13: Low CSAT Rate
C15: =IFERROR(GETPIVOTDATA("Count of ticket_id",'Pivot tables'!$A$3),"N/A") -> 8469 | F15: =IFERROR(GETPIVOTDATA("Average of customer_satisfaction_rating",'Pivot tables'!$A$3),"N/A") -> 2.9913326 | I15: =IFERROR(GETPIVOTDATA("Average of Resolution_Time_Clean",'Pivot tables'!$A$3),"N/A") -> 7.1096866 | L15: =IFERROR('Pivot tables'!C11,"N/A") -> 0.32695714 | O15: =IFERROR('Pivot tables'!D11,"N/A") -> 5700 | R15: =IFERROR('Pivot tables'!D193,"N/A") -> 0.39797761

Sheet Tickets Data
A1: ticket_id | B1: customer_name | C1: customer_email | D1: customer_age | E1: customer_gender | F1: product_purchased | G1: date_of_purchase | H1: ticket_type | I1: ticket_subject | J1: ticket_description | K1: ticket_status | L1: resolution | M1: ticket_priority | N1: ticket_channel | O1: first_response_at | P1: resolved_at | Q1: customer_satisfaction_rating | R1: resolution_time_hours | S1: is_closed | T1: is_backlog | U1: is_low_csat | V1: Resolution_Time_Clean
A2: 1 | B2: Marisa Obrien | C2: carrollallison@example.com | D2: 32 | E2: Other | F2: GoPro Hero | G2: 44277 | H2: Technical issue | I2: Product setup | J2: I'm having an issue with the {product_purchased}. Please assist. Your billing zip code is: 71701. We appreciate that you have requested a website address. Please double check your email address. I've tried troubleshooting steps mentioned in the user manual, but the issue persists. | K2: Pending Customer Response | M2: Critical | N2: Social media | O2: 45078.511 | S2: 0 | T2: 1 | U2: 0 | V2: =IF(OR(tickets_cleaned[[#This Row],[resolution_time_hours]]="", tickets_cleaned[[#This Row],[resolution_time_hours]]<0),"",tickets_cleaned[[#This Row],[resolution_time_hours]])
A3: 2 | B3: Jessica Rios | C3: clarkeashley@example.com | D3: 42 | E3: Female | F3: LG Smart TV | G3: 44338 | H3: Technical issue | I3: Peripheral compatibility | J3: I'm having an issue with the {product_purchased}. Please assist. If you need to change an existing product. I'm having an issue with the {product_purchased}. Please assist. If The issue I'm facing is intermittent. Sometimes it works fine, but other times it acts up unexpectedly. | K3: Pending Customer Response | M3: Critical | N3: Chat | O3: 45078.698 | S3: 0 | T3: 1 | U3: 0 | V3: =IF(OR(tickets_cleaned[[#This Row],[resolution_time_hours]]="", tickets_cleaned[[#This Row],[resolution_time_hours]]<0),"",tickets_cleaned[[#This Row],[resolution_time_hours]])
A4: 3 | B4: Christopher Robbins | C4: gonzalestracy@example.com | D4: 48 | E4: Other | F4: Dell XPS | G4: 44026 | H4: Technical issue | I4: Network problem | J4: I'm facing a problem with my {product_purchased}. The {product_purchased} is not turning on. It was working fine until yesterday, but now it doesn't respond. 1.8.3 I really I'm using the original charger that came with my {product_purchased}, but it's not charging properly. | K4: Closed | L4: Case maybe show recently my computer follow. | M4: Low | N4: Social media | O4: 45078.468 | P4: 45078.754 | Q4: 3 | R4: 6 | S4: 1 | T4: 0 | U4: 0 | V4: =IF(OR(tickets_cleaned[[#This Row],[resolution_time_hours]]="", tickets_cleaned[[#This Row],[resolution_time_hours]]<0),"",tickets_cleaned[[#This Row],[resolution_time_hours]]) -> 6
A5: 4 | B5: Christina Dillon | C5: bradleyolson@example.org | D5: 27 | E5: Female | F5: Microsoft Office | G5: 44148 | H5: Billing inquiry | I5: Account access | J5: I'm having an issue with the {product_purchased}. Please assist. If you have a problem you're interested in and I'd love to see this happen, please check out the Feedback. I've already contacted customer support multiple times, but the issue remains unresolved. | K5: Closed | L5: Try capital clearly never color toward story. | M5: Low | N5: Social media | O5: 45078.312 | P5: 45078.082 | Q5: 3 | S5: 1 | T5: 0 | U5: 0 | V5: =IF(OR(tickets_cleaned[[#This Row],[resolution_time_hours]]="", tickets_cleaned[[#This Row],[resolution_time_hours]]<0),"",tickets_cleaned[[#This Row],[resolution_time_hours]])
A6: 5 | B6: Alexander Carroll | C6: bradleymark@example.com | D6: 67 | E6: Female | F6: Autodesk AutoCAD | G6: 43865 | H6: Billing inquiry | I6: Data loss | J6: I'm having an issue with the {product_purchased}. Please assist. Note: The seller is not responsible for any damages arising out of the delivery of the battleground game. Please have the game in good condition and shipped to you I've noticed a sudden decrease in battery life on my {product_purchased}. It used to last much longer. | K6: Closed | L6: West decision evidence bit. | M6: Low | N6: Email | O6: 45078.009 | P6: 45078.829 | Q6: 1 | R6: 19 | S6: 1 | T6: 0 | U6: 1 | V6: =IF(OR(tickets_cleaned[[#This Row],[resolution_time_hours]]="", tickets_cleaned[[#This Row],[resolution_time_hours]]<0),"",tickets_cleaned[[#This Row],[resolution_time_hours]]) -> 19
A7: 6 | B7: Rebecca Fleming | C7: sheenasmith@example.com | D7: 53 | E7: Male | F7: Microsoft Office | G7: 44040 | H7: Cancellation request | I7: Payment issue | J7: I'm facing a problem with my {product_purchased}. The {product_purchased} is not turning on. It was working fine until yesterday, but now it doesn't respond. To remove the new {product_purch I've checked for any available software updates for my {product_purchased}, but there are none. | K7: Open | M7: Low | N7: Social media | S7: 0 | T7: 1 | U7: 0 | V7: =IF(OR(tickets_cleaned[[#This Row],[resolution_time_hours]]="", tickets_cleaned[[#This Row],[resolution_time_hours]]<0),"",tickets_cleaned[[#This Row],[resolution_time_hours]])
A8: 7 | B8: Jacqueline Wright | C8: donaldkeith@example.org | D8: 24 | E8: Other | F8: Microsoft Surface | G8: 43884 | H8: Product inquiry | I8: Refund request | J8: I'm unable to access my {product_purchased} account. It keeps displaying an 'Invalid Credentials' error, even though I'm using the correct login information. How can I regain access to my account? Solution 1 I'm unable to find the option to perform the desired action in the {product_purchased}. Could you please guide me through the steps? | K8: Open | M8: Critical | N8: Social media | S8: 0 | T8: 1 | U8: 0 | V8: =IF(OR(tickets_cleaned[[#This Row],[resolution_time_hours]]="", tickets_cleaned[[#This Row],[resolution_time_hours]]<0),"",tickets_cleaned[[#This Row],[resolution_time_hours]])
A9: 8 | B9: Denise Lee | C9: joelwilliams@example.com | D9: 23 | E9: Male | F9: Philips Hue Lights | G9: 44052 | H9: Refund request | I9: Battery life | J9: I'm having an issue with the {product_purchased}. Please assist. (Thanks) I will contact all my suppliers and confirm. Please try and find out whether their inventory is currently stocked, or any other reason. I am I've performed a factory reset on my {product_purchased}, hoping it would resolve the problem, but it didn't help. | K9: Open | M9: Critical | N9: Social media | S9: 0 | T9: 1 | U9: 0 | V9: =IF(OR(tickets_cleaned[[#This Row],[resolution_time_hours]]="", tickets_cleaned[[#This Row],[resolution_time_hours]]<0),"",tickets_cleaned[[#This Row],[resolution_time_hours]])
A10: 9 | B10: Nicolas Wilson | C10: joshua24@example.com | D10: 60 | E10: Other | F10: Fitbit Versa Smartwatch | G10: 44028 | H10: Technical issue | I10: Installation support | J10: I'm having an issue with the {product_purchased}. Please assist. Thank you. {product_purchased} is not the exact type you might prefer, they use the exact same method for different uses. Please help I've recently updated the firmware of my {product_purchased}, and the issue started happening afterward. Could it be related to the update? | K10: Pending Customer Response | M10: Low | N10: Social media | O10: 45078.439 | S10: 0 | T10: 1 | U10: 0 | V10: =IF(OR(tickets_cleaned[[#This Row],[resolution_time_hours]]="", tickets_cleaned[[#This Row],[resolution_time_hours]]<0),"",tickets_cleaned[[#This Row],[resolution_time_hours]])
A11: 10 | B11: William Dawson | C11: clopez@example.com | D11: 27 | E11: Male | F11: Dyson Vacuum Cleaner | G11: 43896 | H11: Refund request | I11: Payment issue | J11: My {product_purchased} is making strange noises and not functioning properly. I suspect there might be a hardware issue. Can you please help me with this? } If we can, please send a "request" to dav The issue I'm facing is intermittent. Sometimes it works fine, but other times it acts up unexpectedly. | K11: Pending Customer Response | M11: Critical | N11: Phone | O11: 45078.393 | S11: 0 | T11: 1 | U11: 0 | V11: =IF(OR(tickets_cleaned[[#This Row],[resolution_time_hours]]="", tickets_cleaned[[#This Row],[resolution_time_hours]]<0),"",tickets_cleaned[[#This Row],[resolution_time_hours]])
A12: 11 | B12: Joseph Moreno | C12: mbrown@example.org | D12: 48 | E12: Male | F12: Nintendo Switch | G12: 44215 | H12: Cancellation request | I12: Data loss | J12: I'm having an issue with the {product_purchased}. Please assist. 1-800-799-0808. Product Search: What's New in 2-3-4-5? Report Feedback Customer Service is your best I'm using the original charger that came with my {product_purchased}, but it's not charging properly. | K12: Closed | L12: Measure tonight surface feel forward. | M12: High | N12: Phone | O12: 45078.741 | P12: 45077.994 | Q12: 1 | S12: 1 | T12: 0 | U12: 1 | V12: =IF(OR(tickets_cleaned[[#This Row],[resolution_time_hours]]="", tickets_cleaned[[#This Row],[resolution_time_hours]]<0),"",tickets_cleaned[[#This Row],[resolution_time_hours]])
A13: 12 | B13: Brandon Arnold | C13: davisjohn@example.net | D13: 51 | E13: Male | F13: Microsoft Xbox Controller | G13: 44493 | H13: Product inquiry | I13: Software bug | J13: I'm having an issue with the {product_purchased}. Please assist. 4. It is possible that we cannot find some type of text or a product name to identify someone like Mr. Brown. 5. On the I've reviewed the troubleshooting steps on the official support website, but they didn't resolve the problem. | K13: Closed | L13: Measure there house management pick knowledge trade. | M13: High | N13: Chat | O13: 45078.504 | P13: 45078.394 | Q13: 1 | S13: 1 | T13: 0 | U13: 1 | V13: =IF(OR(tickets_cleaned[[#This Row],[resolution_time_hours]]="", tickets_cleaned[[#This Row],[resolution_time_hours]]<0),"",tickets_cleaned[[#This Row],[resolution_time_hours]])
A14: 13 | B14: Tamara Hahn | C14: jensenwilliam@example.net | D14: 27 | E14: Other | F14: Nintendo Switch Pro Controller | G14: 44342 | H14: Technical issue | I14: Hardware issue | J14: I'm having an issue with the {product_purchased}. Please assist. CQW: Why didn't I send him the invoice? Thanks a lot. L: He's like the best customer I've met. I've noticed that the issue occurs consistently when I use a specific feature or application on my {product_purchased}. | K14: Pending Customer Response | M14: Low | N14: Chat | O14: 45078.794 | S14: 0 | T14: 1 | U14: 0 | V14: =IF(OR(tickets_cleaned[[#This Row],[resolution_time_hours]]="", tickets_cleaned[[#This Row],[resolution_time_hours]]<0),"",tickets_cleaned[[#This Row],[resolution_time_hours]])
A15: 14 | B15: Sandra Barnes | C15: gwendolyn51@example.net | D15: 65 | E15: Other | F15: Nest Thermostat | G15: 44025 | H15: Technical issue | I15: Product setup | J15: I've recently set up my {product_purchased}, but it fails to connect to any available networks. What steps should I take to troubleshoot this issue? I can't find the 'Product_IP' field of the I'm concerned about the security of my {product_purchased} and would like to ensure that my data is safe. | K15: Pending Customer Response | M15: Low | N15: Chat | O15: 45078.858 | S15: 0 | T15: 1 | U15: 0 | V15: =IF(OR(tickets_cleaned[[#This Row],[resolution_time_hours]]="", tickets_cleaned[[#This Row],[resolution_time_hours]]<0),"",tickets_cleaned[[#This Row],[resolution_time_hours]])
A16: 15 | B16: Amy Hill | C16: medinasteven@example.net | D16: 48 | E16: Female | F16: Sony PlayStation | G16: 43890 | H16: Billing inquiry | I16: Product setup | J16: I'm having an issue with the {product_purchased}. Please assist. Product Name: TPUBASK3E3KQ0 Join Date: Oct 2007 Posts: 11,532 Quote: I've recently updated the firmware of my {product_purchased}, and the issue started happening afterward. Could it be related to the update? | K16: Closed | L16: Officer moment world sing parent available. | M16: High | N16: Chat | O16: 45078.266 | P16: 45077.965 | Q16: 4 | S16: 1 | T16: 0 | U16: 0 | V16: =IF(OR(tickets_cleaned[[#This Row],[resolution_time_hours]]="", tickets_cleaned[[#This Row],[resolution_time_hours]]<0),"",tickets_cleaned[[#This Row],[resolution_time_hours]])
A17: 16 | B17: Elizabeth Foley | C17: amy41@example.net | D17: 18 | E17: Other | F17: GoPro Action Camera | G17: 44371 | H17: Billing inquiry | I17: Product recommendation | J17: I'm having an issue with the {product_purchased}. Please assist. Please note, you might have already paid for this product, which means spectators are not buying any of the products from the sale as their donations will go straight I've noticed a sudden decrease in battery life on my {product_purchased}. It used to last much longer. | K17: Pending Customer Response | M17: High | N17: Social media | O17: 45078.632 | S17: 0 | T17: 1 | U17: 0 | V17: =IF(OR(tickets_cleaned[[#This Row],[resolution_time_hours]]="", tickets_cleaned[[#This Row],[resolution_time_hours]]<0),"",tickets_cleaned[[#This Row],[resolution_time_hours]])
A18: 17 | B18: Julia Salazar | C18: watkinsbarbara@example.com | D18: 63 | E18: Other | F18: Xbox | G18: 44482 | H18: Product inquiry | I18: Account access | J18: I'm having an issue with the {product_purchased}. Please assist. - Acknowledgement: Thanks to Dan for the tip. When you purchase a new product from my store or from your local retailer, they will also provide I'm concerned about the security of my {product_purchased} and would like to ensure that my data is safe. | K18: Closed | L18: Seek evidence book collection catch. | M18: Critical | N18: Chat | O18: 45078.824 | P18: 45078.666 | Q18: 4 | S18: 1 | T18: 0 | U18: 0 | V18: =IF(OR(tickets_cleaned[[#This Row],[resolution_time_hours]]="", tickets_cleaned[[#This Row],[resolution_time_hours]]<0),"",tickets_cleaned[[#This Row],[resolution_time_hours]])
A19: 18 | B19: Joshua Castillo | C19: mooredeborah@example.org | D19: 56 | E19: Female | F19: Microsoft Xbox Controller | G19: 44081 | H19: Product inquiry | I19: Payment issue | J19: I'm having an issue with the {product_purchased}. Please assist. Thanks!" * [0] - [0] - [0] - [0] If this product is sold and you have not used any I've reviewed the troubleshooting steps on the official support website, but they didn't resolve the problem. | K19: Pending Customer Response | M19: High | N19: Chat | O19: 45078.878 | S19: 0 | T19: 1 | U19: 0 | V19: =IF(OR(tickets_cleaned[[#This Row],[resolution_time_hours]]="", tickets_cleaned[[#This Row],[resolution_time_hours]]<0),"",tickets_cleaned[[#This Row],[resolution_time_hours]])
A20: 19 | B20: Wendy Davis | C20: brenda20@example.net | D20: 19 | E20: Male | F20: LG Washing Machine | G20: 44462 | H20: Product inquiry | I20: Peripheral compatibility | J20: I'm having an issue with the {product_purchased}. Please assist. I want to be an active member of our community on YouTube... The issue I'm facing is intermittent. Sometimes it works fine, but other times it acts up unexpectedly. | K20: Open | M20: High | N20: Social media | S20: 0 | T20: 1 | U20: 0 | V20: =IF(OR(tickets_cleaned[[#This Row],[resolution_time_hours]]="", tickets_cleaned[[#This Row],[resolution_time_hours]]<0),"",tickets_cleaned[[#This Row],[resolution_time_hours]])
A21: 20 | B21: Jeffrey Robertson | C21: jameslopez@example.com | D21: 39 | E21: Female | F21: Canon EOS | G21: 44263 | H21: Refund request | I21: Software bug | J21: I'm having an issue with the {product_purchased}. Please assist. I'm having an issue with the product_purchased}. Please assist. Customer Reviewer: My Husband was able to take an order from Apple I've checked for any available software updates for my {product_purchased}, but there are none. | K21: Closed | L21: Wish mouth build resource though. | M21: Low | N21: Chat | O21: 45078.032 | P21: 45078.854 | Q21: 5 | R21: 19 | S21: 1 | T21: 0 | U21: 0 | V21: =IF(OR(tickets_cleaned[[#This Row],[resolution_time_hours]]="", tickets_cleaned[[#This Row],[resolution_time_hours]]<0),"",tickets_cleaned[[#This Row],[resolution_time_hours]]) -> 19
A22: 21 | B22: Suzanne Holmes | C22: rogermcgrath@example.net | D22: 28 | E22: Other | F22: HP Pavilion | G22: 44347 | H22: Refund request | I22: Payment issue | J22: I'm having an issue with the {product_purchased}. Please assist. " -name "Microsoft Surface Pro. " " -version 1.10.2 "1.10.2" " -usage I've checked for any available software updates for my {product_purchased}, but there are none. | K22: Pending Customer Response | M22: High | N22: Chat | O22: 45078.214 | S22: 0 | T22: 1 | U22: 0 | V22: =IF(OR(tickets_cleaned[[#This Row],[resolution_time_hours]]="", tickets_cleaned[[#This Row],[resolution_time_hours]]<0),"",tickets_cleaned[[#This Row],[resolution_time_hours]])
A23: 22 | B23: Tanner Conley | C23: zbond@example.net | D23: 66 | E23: Male | F23: Fitbit Versa Smartwatch | G23: 43865 | H23: Cancellation request | I23: Installation support | J23: I'm having an issue with the {product_purchased}. Please assist. The email address should change to: customer@julietr.com, as there is a unique id number unique for each product. You I've tried different settings and configurations on my {product_purchased}, but the issue persists. | K23: Pending Customer Response | M23: Critical | N23: Social media | O23: 45077.998 | S23: 0 | T23: 1 | U23: 0 | V23: =IF(OR(tickets_cleaned[[#This Row],[resolution_time_hours]]="", tickets_cleaned[[#This Row],[resolution_time_hours]]<0),"",tickets_cleaned[[#This Row],[resolution_time_hours]])
A24: 23 | B24: Stephanie Nelson DVM | C24: ljohnson@example.org | D24: 54 | E24: Female | F24: Xbox | G24: 43872 | H24: Cancellation request | I24: Delivery problem | J24: I'm having an issue with the {product_purchased}. Please assist. (And if need be this time, that could help.) 1.3.2.1 Update my version to 3.0 or more. The issue I'm facing is intermittent. Sometimes it works fine, but other times it acts up unexpectedly. | K24: Open | M24: Medium | N24: Social media | S24: 0 | T24: 1 | U24: 0 | V24: =IF(OR(tickets_cleaned[[#This Row],[resolution_time_hours]]="", tickets_cleaned[[#This Row],[resolution_time_hours]]<0),"",tickets_cleaned[[#This Row],[resolution_time_hours]])
A25: 24 | B25: Antonio Scott | C25: carlsonmatthew@example.org | D25: 63 | E25: Female | F25: Nintendo Switch Pro Controller | G25: 44414 | H25: Technical issue | I25: Refund request | J25: I'm having an issue with the {product_purchased}. Please assist. I'll take care of those. I've performed a factory reset on my {product_purchased}, hoping it would resolve the problem, but it didn't help. | K25: Pending Customer Response | M25: Low | N25: Social media | O25: 45078.379 | S25: 0 | T25: 1 | U25: 0 | V25: =IF(OR(tickets_cleaned[[#This Row],[resolution_time_hours]]="", tickets_cleaned[[#This Row],[resolution_time_hours]]<0),"",tickets_cleaned[[#This Row],[resolution_time_hours]])
A26: 25 | B26: John Cuevas | C26: lbarron@example.org | D26: 19 | E26: Male | F26: Amazon Kindle | G26: 44341 | H26: Product inquiry | I26: Display issue | J26: I'm having an issue with the {product_purchased}. Please assist. {product_purchased} does not represent the price which you received by the day immediately before the shipment date. In many cases, this is the I've noticed a sudden decrease in battery life on my {product_purchased}. It used to last much longer. | K26: Open | M26: Critical | N26: Email | S26: 0 | T26: 1 | U26: 0 | V26: =IF(OR(tickets_cleaned[[#This Row],[resolution_time_hours]]="", tickets_cleaned[[#This Row],[resolution_time_hours]]<0),"",tickets_cleaned[[#This Row],[resolution_time_hours]])
A27: 26 | B27: Gregory Bautista | C27: johnstonbeth@example.com | D27: 35 | E27: Other | F27: HP Pavilion | G27: 44382 | H27: Product inquiry | I27: Refund request | J27: My {product_purchased} is making strange noises and not functioning properly. I suspect there might be a hardware issue. Can you please help me with this? Thank you, Thank you for posting. It took me a I'm experiencing this issue on multiple devices of the same model, so it seems to be a widespread problem. | K27: Pending Customer Response | M27: Medium | N27: Social media | O27: 45078.793 | S27: 0 | T27: 1 | U27: 0 | V27: =IF(OR(tickets_cleaned[[#This Row],[resolution_time_hours]]="", tickets_cleaned[[#This Row],[resolution_time_hours]]<0),"",tickets_cleaned[[#This Row],[resolution_time_hours]])
A28: 27 | B28: Ryan Sharp | C28: pmercado@example.org | D28: 22 | E28: Other | F28: Lenovo ThinkPad | G28: 43953 | H28: Billing inquiry | I28: Cancellation request | J28: I'm encountering a software bug in the {product_purchased}. Whenever I try to perform a specific action, the application crashes. Are there any updates or fixes available? On Windows Vista, this is not possible. If you are I've performed a factory reset on my {product_purchased}, hoping it would resolve the problem, but it didn't help. | K28: Pending Customer Response | M28: Low | N28: Social media | O28: 45078.835 | S28: 0 | T28: 1 | U28: 0 | V28: =IF(OR(tickets_cleaned[[#This Row],[resolution_time_hours]]="", tickets_cleaned[[#This Row],[resolution_time_hours]]<0),"",tickets_cleaned[[#This Row],[resolution_time_hours]])
A29: 28 | B29: Michael Mcdowell | C29: jeffersonmichael@example.net | D29: 21 | E29: Other | F29: Fitbit Charge | G29: 44116 | H29: Cancellation request | I29: Product setup | J29: I'm having an issue with the {product_purchased}. Please assist. {{product_purchased}} must be a valid email address for your order and are valid for one week in advance. Please make your purchases as quickly as possible The issue I'm facing is intermittent. Sometimes it works fine, but other times it acts up unexpectedly. | K29: Open | M29: High | N29: Phone | S29: 0 | T29: 1 | U29: 0 | V29: =IF(OR(tickets_cleaned[[#This Row],[resolution_time_hours]]="", tickets_cleaned[[#This Row],[resolution_time_hours]]<0),"",tickets_cleaned[[#This Row],[resolution_time_hours]])
A30: 29 | B30: Christine Wang | C30: garciastacy@example.com | D30: 30 | E30: Other | F30: Fitbit Charge | G30: 43992 | H30: Technical issue | I30: Product recommendation | J30: I'm having an issue with the {product_purchased}. Please assist. Thank you." A statement from the consumer group had been released by Microsoft late on Tuesday afternoon. "The purchase of this product was made using a contract with I'm using the original charger that came with my {product_purchased}, but it's not charging properly. | K30: Closed | L30: Soldier we such inside. | M30: Critical | N30: Phone | O30: 45077.97 | P30: 45078.252 | Q30: 5 | R30: 6 | S30: 1 | T30: 0 | U30: 0 | V30: =IF(OR(tickets_cleaned[[#This Row],[resolution_time_hours]]="", tickets_cleaned[[#This Row],[resolution_time_hours]]<0),"",tickets_cleaned[[#This Row],[resolution_time_hours]]) -> 6
A31: 30 | B31: Austin George | C31: shericase@example.net | D31: 67 | E31: Male | F31: Xbox | G31: 44191 | H31: Cancellation request | I31: Cancellation request | J31: I'm having an issue with the {product_purchased}. Please assist. It's not possible to remove the missing content. I've already contacted customer support multiple times, but the issue remains unresolved. | K31: Closed | L31: Firm sort voice above which site arrive. | M31: Medium | N31: Phone | O31: 45078.038 | P31: 45078.766 | Q31: 1 | R31: 17 | S31: 1 | T31: 0 | U31: 1 | V31: =IF(OR(tickets_cleaned[[#This Row],[resolution_time_hours]]="", tickets_cleaned[[#This Row],[resolution_time_hours]]<0),"",tickets_cleaned[[#This Row],[resolution_time_hours]]) -> 17
A32: 31 | B32: Wendy Roberts | C32: jessicahenderson@example.net | D32: 22 | E32: Other | F32: Adobe Photoshop | G32: 44224 | H32: Billing inquiry | I32: Product setup | J32: I'm having an issue with the {product_purchased}. Please assist. I'm using a brand new product. What a strange situation. I've just purchased a brand new one. What to do? I've noticed that the issue occurs consistently when I use a specific feature or application on my {product_purchased}. | K32: Open | M32: Low | N32: Email | S32: 0 | T32: 1 | U32: 0 | V32: =IF(OR(tickets_cleaned[[#This Row],[resolution_time_hours]]="", tickets_cleaned[[#This Row],[resolution_time_hours]]<0),"",tickets_cleaned[[#This Row],[resolution_time_hours]])
A33: 32 | B33: Robert Wilson | C33: zstewart@example.org | D33: 60 | E33: Male | F33: GoPro Action Camera | G33: 44550 | H33: Technical issue | I33: Product compatibility | J33: I'm having an issue with the {product_purchased}. Please assist. The seller has sold the item for $29.89. When we receive your replacement, we will exchange the item for a full refund or exchange immediately upon I've already contacted customer support multiple times, but the issue remains unresolved. | K33: Closed | L33: Certain myself month past tree benefit. | M33: Medium | N33: Social media | O33: 45078.279 | P33: 45078.303 | Q33: 3 | R33: 0 | S33: 1 | T33: 0 | U33: 0 | V33: =IF(OR(tickets_cleaned[[#This Row],[resolution_time_hours]]="", tickets_cleaned[[#This Row],[resolution_time_hours]]<0),"",tickets_cleaned[[#This Row],[resolution_time_hours]]) -> 0
A34: 33 | B34: Christina Gray | C34: greenkeith@example.net | D34: 36 | E34: Female | F34: Fitbit Charge | G34: 44537 | H34: Billing inquiry | I34: Product recommendation | J34: I've noticed a software bug in the {product_purchased} app. It's causing data loss and unexpected errors. How can I resolve this issue? I need assistance as soon as possible because it's affecting my work and productivity. | K34: Pending Customer Response | M34: Medium | N34: Chat | O34: 45078.817 | S34: 0 | T34: 1 | U34: 0 | V34: =IF(OR(tickets_cleaned[[#This Row],[resolution_time_hours]]="", tickets_cleaned[[#This Row],[resolution_time_hours]]<0),"",tickets_cleaned[[#This Row],[resolution_time_hours]])
A35: 34 | B35: Timothy Lyons | C35: darlenelee@example.org | D35: 50 | E35: Male | F35: Autodesk AutoCAD | G35: 44539 | H35: Refund request | I35: Hardware issue | J35: I'm having an issue with the {product_purchased}. Please assist. We hope that every vendor takes the time it takes in to do the following: "Remove the product from your account - notify consumers, call them, make their I'm concerned about the security of my {product_purchased} and would like to ensure that my data is safe. | K35: Closed | L35: However financial development significant camera job every. | M35: Critical | N35: Social media | O35: 45078.084 | P35: 45078.768 | Q35: 5 | R35: 16 | S35: 1 | T35: 0 | U35: 0 | V35: =IF(OR(tickets_cleaned[[#This Row],[resolution_time_hours]]="", tickets_cleaned[[#This Row],[resolution_time_hours]]<0),"",tickets_cleaned[[#This Row],[resolution_time_hours]]) -> 16
A36: 35 | B36: Stacy Jones | C36: fernandezmark@example.org | D36: 27 | E36: Male | F36: Microsoft Xbox Controller | G36: 44295 | H36: Refund request | I36: Installation support | J36: I'm having an issue with the {product_purchased}. Please assist. 3-3 We are in, the first day, at the {product_purchased}. Please assist. 3-2 Please assist us I've recently updated the firmware of my {product_purchased}, and the issue started happening afterward. Could it be related to the update? | K36: Pending Customer Response | M36: Low | N36: Chat | O36: 45078.868 | S36: 0 | T36: 1 | U36: 0 | V36: =IF(OR(tickets_cleaned[[#This Row],[resolution_time_hours]]="", tickets_cleaned[[#This Row],[resolution_time_hours]]<0),"",tickets_cleaned[[#This Row],[resolution_time_hours]])
A37: 36 | B37: Joann King | C37: jessica10@example.org | D37: 24 | E37: Other | F37: GoPro Hero | G37: 44117 | H37: Cancellation request | I37: Product recommendation | J37: I've recently set up my {product_purchased}, but it fails to connect to any available networks. What steps should I take to troubleshoot this issue? If you know the answer, please let me know. Do I I've noticed a sudden decrease in battery life on my {product_purchased}. It used to last much longer. | K37: Closed | L37: Reach paper ability effort learn. | M37: High | N37: Chat | O37: 45078.331 | P37: 45078.01 | Q37: 1 | S37: 1 | T37: 0 | U37: 1 | V37: =IF(OR(tickets_cleaned[[#This Row],[resolution_time_hours]]="", tickets_cleaned[[#This Row],[resolution_time_hours]]<0),"",tickets_cleaned[[#This Row],[resolution_time_hours]])
A38: 37 | B38: Ruben Henry | C38: katherinehoward@example.net | D38: 65 | E38: Female | F38: Canon EOS | G38: 43904 | H38: Refund request | I38: Hardware issue | J38: I'm having an issue with the {product_purchased}. Please assist. I have to ask for support from you, the customers, before the item's arrival and I can't do that. In the short term, will you pay me I've followed the troubleshooting steps mentioned in the user manual, but the issue persists. | K38: Pending Customer Response | M38: Medium | N38: Email | O38: 45078.661 | S38: 0 | T38: 1 | U38: 0 | V38: =IF(OR(tickets_cleaned[[#This Row],[resolution_time_hours]]="", tickets_cleaned[[#This Row],[resolution_time_hours]]<0),"",tickets_cleaned[[#This Row],[resolution_time_hours]])
A39: 38 | B39: Morgan Wagner | C39: elizabethlamb@example.com | D39: 39 | E39: Female | F39: Amazon Kindle | G39: 44076 | H39: Product inquiry | I39: Product compatibility | J39: I've forgotten my password for my {product_purchased} account, and the password reset option is not working. How can I recover my account? I can reset my password by entering the following: My password still valid: password is expired I've recently updated the firmware of my {product_purchased}, and the issue started happening afterward. Could it be related to the update? | K39: Open | M39: Medium | N39: Chat | S39: 0 | T39: 1 | U39: 0 | V39: =IF(OR(tickets_cleaned[[#This Row],[resolution_time_hours]]="", tickets_cleaned[[#This Row],[resolution_time_hours]]<0),"",tickets_cleaned[[#This Row],[resolution_time_hours]])
A40: 39 | B40: Kevin Ingram | C40: victor62@example.net | D40: 19 | E40: Male | F40: Google Pixel | G40: 44449 | H40: Technical issue | I40: Account access | J40: I'm having an issue with the {product_purchased}. Please assist. 1. Do I need to purchase a refund? There is a way to purchase a refund from ZEROHITS, but there's not a I'm unable to find the option to perform the desired action in the {product_purchased}. Could you please guide me through the steps? | K40: Closed | L40: North second between this cell opportunity movement. | M40: Critical | N40: Phone | O40: 45078.782 | P40: 45077.912 | Q40: 3 | S40: 1 | T40: 0 | U40: 0 | V40: =IF(OR(tickets_cleaned[[#This Row],[resolution_time_hours]]="", tickets_cleaned[[#This Row],[resolution_time_hours]]<0),"",tickets_cleaned[[#This Row],[resolution_time_hours]])
A41: 40 | B41: Michael Oneal | C41: stevenburns@example.net | D41: 33 | E41: Other | F41: Amazon Echo | G41: 44491 | H41: Product inquiry | I41: Account access | J41: I'm having an issue with the {product_purchased}. Please assist. I have a new account in the system and a new user. I'm having this issue Error: [System.CollectedMessage.ThrowBack I'm concerned about the security of my {product_purchased} and would like to ensure that my data is safe. | K41: Pending Customer Response | M41: Medium | N41: Social media | O41: 45077.93 | S41: 0 | T41: 1 | U41: 0 | V41: =IF(OR(tickets_cleaned[[#This Row],[resolution_time_hours]]="", tickets_cleaned[[#This Row],[resolution_time_hours]]<0),"",tickets_cleaned[[#This Row],[resolution_time_hours]])
A42: 41 | B42: Casey Tran | C42: shawn54@example.net | D42: 19 | E42: Female | F42: PlayStation | G42: 44234 | H42: Product inquiry | I42: Installation support | J42: I've recently set up my {product_purchased}, but it fails to connect to any available networks. What steps should I take to troubleshoot this issue? The next step is to resolve this issue if the user is not I've noticed that the issue occurs consistently when I use a specific feature or application on my {product_purchased}. | K42: Pending Customer Response | M42: Low | N42: Phone | O42: 45078.383 | S42: 0 | T42: 1 | U42: 0 | V42: =IF(OR(tickets_cleaned[[#This Row],[resolution_time_hours]]="", tickets_cleaned[[#This Row],[resolution_time_hours]]<0),"",tickets_cleaned[[#This Row],[resolution_time_hours]])
A43: 42 | B43: Katie Mitchell | C43: sheila78@example.org | D43: 35 | E43: Male | F43: Dell XPS | G43: 44356 | H43: Billing inquiry | I43: Product compatibility | J43: I'm facing a problem with my {product_purchased}. The {product_purchased} is not turning on. It was working fine until yesterday, but now it doesn't respond. If I'd just switched to a The issue I'm facing is intermittent. Sometimes it works fine, but other times it acts up unexpectedly. | K43: Closed | L43: Start book field officer seem make. | M43: Critical | N43: Chat | O43: 45078.851 | P43: 45078.614 | Q43: 3 | S43: 1 | T43: 0 | U43: 0 | V43: =IF(OR(tickets_cleaned[[#This Row],[resolution_time_hours]]="", tickets_cleaned[[#This Row],[resolution_time_hours]]<0),"",tickets_cleaned[[#This Row],[resolution_time_hours]])
A44: 43 | B44: Justin Giles | C44: woodmargaret@example.org | D44: 22 | E44: Male | F44: Samsung Galaxy | G44: 44114 | H44: Product inquiry | I44: Product compatibility | J44: I'm having an issue with the {product_purchased}. Please assist. The product_purchased attribute does not exist on your user's product. This is so that you can configure the {product_purchased} I need assistance as soon as possible because it's affecting my work and productivity. | K44: Pending Customer Response | M44: Medium | N44: Phone | O44: 45078.779 | S44: 0 | T44: 1 | U44: 0 | V44: =IF(OR(tickets_cleaned[[#This Row],[resolution_time_hours]]="", tickets_cleaned[[#This Row],[resolution_time_hours]]<0),"",tickets_cleaned[[#This Row],[resolution_time_hours]])
A45: 44 | B45: Michael Allison | C45: abowen@example.org | D45: 54 | E45: Female | F45: iPhone | G45: 43846 | H45: Technical issue | I45: Hardware issue | J45: I'm having an issue with the {product_purchased}. Please assist. Thank you." The issue occurred after Amazon started a tool to deal with a problem like this (see page 36 of the FAQ): "The product is not I've recently updated the firmware of my {product_purchased}, and the issue started happening afterward. Could it be related to the update? | K45: Open | M45: Low | N45: Email | S45: 0 | T45: 1 | U45: 0 | V45: =IF(OR(tickets_cleaned[[#This Row],[resolution_time_hours]]="", tickets_cleaned[[#This Row],[resolution_time_hours]]<0),"",tickets_cleaned[[#This Row],[resolution_time_hours]])
A46: 45 | B46: Donald Gibbs | C46: laura33@example.org | D46: 34 | E46: Other | F46: HP Pavilion | G46: 44464 | H46: Refund request | I46: Product compatibility | J46: I'm having an issue with the {product_purchased}. Please assist. I wanted a picture for my 3DS, but I already bought a lot of items, so I found an online cart: "Fountain of Dreams Collection I'm unable to find the option to perform the desired action in the {product_purchased}. Could you please guide me through the steps? | K46: Closed | L46: Over read region lawyer much speech control. | M46: Critical | N46: Email | O46: 45078.249 | P46: 45078.139 | Q46: 2 | S46: 1 | T46: 0 | U46: 1 | V46: =IF(OR(tickets_cleaned[[#This Row],[resolution_time_hours]]="", tickets_cleaned[[#This Row],[resolution_time_hours]]<0),"",tickets_cleaned[[#This Row],[resolution_time_hours]])
A47: 46 | B47: Timothy Sutton | C47: david40@example.org | D47: 65 | E47: Female | F47: LG Smart TV | G47: 44228 | H47: Product inquiry | I47: Cancellation request | J47: I'm having an issue with the {product_purchased}. Please assist. Thanks". "As a result I'm having an issue with the 1.0 patch. Please assist." "All I'm asking is to update I'm concerned about the security of my {product_purchased} and would like to ensure that my data is safe. | K47: Open | M47: Low | N47: Chat | S47: 0 | T47: 1 | U47: 0 | V47: =IF(OR(tickets_cleaned[[#This Row],[resolution_time_hours]]="", tickets_cleaned[[#This Row],[resolution_time_hours]]<0),"",tickets_cleaned[[#This Row],[resolution_time_hours]])
A48: 47 | B48: Cassandra Richards | C48: abigail06@example.com | D48: 50 | E48: Female | F48: Nintendo Switch Pro Controller | G48: 44119 | H48: Refund request | I48: Network problem | J48: I'm having an issue with the {product_purchased}. Please assist. We have not yet provided an address or a name for this product. If this website does not exist, please contact us with this information and we will provide it. I need assistance as soon as possible because it's affecting my work and productivity. | K48: Closed | L48: Audience food pretty cut. | M48: High | N48: Phone | O48: 45078.155 | P48: 45078.392 | Q48: 1 | R48: 5 | S48: 1 | T48: 0 | U48: 1 | V48: =IF(OR(tickets_cleaned[[#This Row],[resolution_time_hours]]="", tickets_cleaned[[#This Row],[resolution_time_hours]]<0),"",tickets_cleaned[[#This Row],[resolution_time_hours]]) -> 5
A49: 48 | B49: Kristen Perry | C49: bevans@example.org | D49: 27 | E49: Female | F49: GoPro Hero | G49: 44041 | H49: Technical issue | I49: Software bug | J49: I'm having an issue with the {product_purchased}. Please assist. This product is not found on, and should NOT come from, this site. Not sure about what this product covers? Product Description I'm experiencing this issue on multiple devices of the same model, so it seems to be a widespread problem. | K49: Closed | L49: Late center interview that. | M49: Medium | N49: Social media | O49: 45078.303 | P49: 45078.25 | Q49: 1 | S49: 1 | T49: 0 | U49: 1 | V49: =IF(OR(tickets_cleaned[[#This Row],[resolution_time_hours]]="", tickets_cleaned[[#This Row],[resolution_time_hours]]<0),"",tickets_cleaned[[#This Row],[resolution_time_hours]])
A50: 49 | B50: Noah Mcknight | C50: juliepowers@example.org | D50: 32 | E50: Other | F50: LG OLED | G50: 44242 | H50: Cancellation request | I50: Network problem | J50: I'm having an issue with the {product_purchased}. Please assist. Please. Don't. Don't see my issue? Please contact me. I'm unable to find the option to perform the desired action in the {product_purchased}. Could you please guide me through the steps? | K50: Open | M50: High | N50: Chat | S50: 0 | T50: 1 | U50: 0 | V50: =IF(OR(tickets_cleaned[[#This Row],[resolution_time_hours]]="", tickets_cleaned[[#This Row],[resolution_time_hours]]<0),"",tickets_cleaned[[#This Row],[resolution_time_hours]])
A51: 50 | B51: Katie Johnson | C51: thomas46@example.net | D51: 44 | E51: Male | F51: Microsoft Office | G51: 44101 | H51: Technical issue | I51: Display issue | J51: I'm having an issue with the {product_purchased}. Please assist. If you've received a refund, please contact Customer Service. Otherwise, please call us at 303.938.2837. I'm having an issue with the I'm concerned about the security of my {product_purchased} and would like to ensure that my data is safe. | K51: Open | M51: Medium | N51: Chat | S51: 0 | T51: 1 | U51: 0 | V51: =IF(OR(tickets_cleaned[[#This Row],[resolution_time_hours]]="", tickets_cleaned[[#This Row],[resolution_time_hours]]<0),"",tickets_cleaned[[#This Row],[resolution_time_hours]])
A52: 51 | B52: Kayla Dunn | C52: ramirezphilip@example.net | D52: 66 | E52: Male | F52: Sony Xperia | G52: 44187 | H52: Refund request | I52: Software bug | J52: I'm encountering a software bug in the {product_purchased}. Whenever I try to perform a specific action, the application crashes. Are there any updates or fixes available? There are several packages that run in memory by default. These I'm experiencing this issue on multiple devices of the same model, so it seems to be a widespread problem. | K52: Open | M52: Medium | N52: Chat | S52: 0 | T52: 1 | U52: 0 | V52: =IF(OR(tickets_cleaned[[#This Row],[resolution_time_hours]]="", tickets_cleaned[[#This Row],[resolution_time_hours]]<0),"",tickets_cleaned[[#This Row],[resolution_time_hours]])
A53: 52 | B53: Tracy White | C53: wvargas@example.com | D53: 64 | E53: Male | F53: LG Smart TV | G53: 44155 | H53: Refund request | I53: Software bug | J53: I've recently set up my {product_purchased}, but it fails to connect to any available networks. What steps should I take to troubleshoot this issue?.......................................................1. Visit https://forum.ejconop I've reviewed the troubleshooting steps on the official support website, but they didn't resolve the problem. | K53: Closed | L53: Might Mrs often stuff. | M53: Medium | N53: Chat | O53: 45078.682 | P53: 45078.439 | Q53: 3 | S53: 1 | T53: 0 | U53: 0 | V53: =IF(OR(tickets_cleaned[[#This Row],[resolution_time_hours]]="", tickets_cleaned[[#This Row],[resolution_time_hours]]<0),"",tickets_cleaned[[#This Row],[resolution_time_hours]])
A54: 53 | B54: Christian Graves | C54: hgriffin@example.org | D54: 54 | E54: Male | F54: Nest Thermostat | G54: 44479 | H54: Refund request | I54: Network problem | J54: I'm having an issue with the {product_purchased}. Please assist. Please. Please. I need assistance as soon as possible because it's affecting my work and productivity. | K54: Closed | L54: More left involve agree station billion would. | M54: High | N54: Social media | O54: 45078.08 | P54: 45078.875 | Q54: 3 | R54: 19 | S54: 1 | T54: 0 | U54: 0 | V54: =IF(OR(tickets_cleaned[[#This Row],[resolution_time_hours]]="", tickets_cleaned[[#This Row],[resolution_time_hours]]<0),"",tickets_cleaned[[#This Row],[resolution_time_hours]]) -> 19
A55: 54 | B55: Casey Reed | C55: sabrina61@example.org | D55: 37 | E55: Male | F55: HP Pavilion | G55: 44424 | H55: Cancellation request | I55: Delivery problem | J55: I'm having an issue with the {product_purchased}. Please assist. If it's not working I can't help you. I've performed a factory reset on my {product_purchased}, hoping it would resolve the problem, but it didn't help. | K55: Closed | L55: Even two pay expect. | M55: Low | N55: Chat | O55: 45078.028 | P55: 45078.435 | Q55: 4 | R55: 9 | S55: 1 | T55: 0 | U55: 0 | V55: =IF(OR(tickets_cleaned[[#This Row],[resolution_time_hours]]="", tickets_cleaned[[#This Row],[resolution_time_hours]]<0),"",tickets_cleaned[[#This Row],[resolution_time_hours]]) -> 9
A56: 55 | B56: Carrie Ayers | C56: natasha18@example.com | D56: 68 | E56: Female | F56: Microsoft Xbox Controller | G56: 44483 | H56: Technical issue | I56: Network problem | J56: I've noticed a software bug in the {product_purchased} app. It's causing data loss and unexpected errors. How can I resolve this issue? For those who live in the U.S., you can use the {product_ I'm unable to find the option to perform the desired action in the {product_purchased}. Could you please guide me through the steps? | K56: Pending Customer Response | M56: Low | N56: Chat | O56: 45078.31 | S56: 0 | T56: 1 | U56: 0 | V56: =IF(OR(tickets_cleaned[[#This Row],[resolution_time_hours]]="", tickets_cleaned[[#This Row],[resolution_time_hours]]<0),"",tickets_cleaned[[#This Row],[resolution_time_hours]])
A57: 56 | B57: Sarah Cole | C57: williamscynthia@example.org | D57: 50 | E57: Female | F57: Nintendo Switch Pro Controller | G57: 44519 | H57: Cancellation request | I57: Software bug | J57: I'm having an issue with the {product_purchased}. Please assist. The requested address will be returned within 3 ‚Äì 9 business days. Please do not hesitate to contact us using the appropriate form. (9 weeks from purchase time I'm unable to find the option to perform the desired action in the {product_purchased}. Could you please guide me through the steps? | K57: Pending Customer Response | M57: Critical | N57: Chat | O57: 45078.469 | S57: 0 | T57: 1 | U57: 0 | V57: =IF(OR(tickets_cleaned[[#This Row],[resolution_time_hours]]="", tickets_cleaned[[#This Row],[resolution_time_hours]]<0),"",tickets_cleaned[[#This Row],[resolution_time_hours]])
A58: 57 | B58: Alison Ford | C58: mcgeebrandon@example.org | D58: 69 | E58: Male | F58: Autodesk AutoCAD | G58: 44552 | H58: Technical issue | I58: Software bug | J58: I'm having an issue with the {product_purchased}. Please assist. I've noticed that the issue occurs consistently when I use a specific feature or application on my {product_purchased}. | K58: Pending Customer Response | M58: Medium | N58: Social media | O58: 45078.44 | S58: 0 | T58: 1 | U58: 0 | V58: =IF(OR(tickets_cleaned[[#This Row],[resolution_time_hours]]="", tickets_cleaned[[#This Row],[resolution_time_hours]]<0),"",tickets_cleaned[[#This Row],[resolution_time_hours]])
A59: 58 | B59: Lori Young | C59: pthomas@example.org | D59: 47 | E59: Other | F59: GoPro Action Camera | G59: 44040 | H59: Refund request | I59: Peripheral compatibility | J59: I'm having an issue with the {product_purchased}. Please assist. Thank you! This product was added to your friend's shopping cart at your friend's favorite store. Sorry, your account is not loaded. I've followed the troubleshooting steps mentioned in the user manual, but the issue persists. | K59: Open | M59: Critical | N59: Email | S59: 0 | T59: 1 | U59: 0 | V59: =IF(OR(tickets_cleaned[[#This Row],[resolution_time_hours]]="", tickets_cleaned[[#This Row],[resolution_time_hours]]<0),"",tickets_cleaned[[#This Row],[resolution_time_hours]])
A60: 59 | B60: Kimberly Mack | C60: lwilliamson@example.net | D60: 27 | E60: Male | F60: Autodesk AutoCAD | G60: 44043 | H60: Technical issue | I60: Product recommendation | J60: I've forgotten my password for my {product_purchased} account, and the password reset option is not working. How can I recover my account? What happens when you lose all of your money without a credit card? The issue I'm facing is intermittent. Sometimes it works fine, but other times it acts up unexpectedly. | K60: Closed | L60: During base sure measure teach time large. | M60: Medium | N60: Phone | O60: 45078.498 | P60: 45078.199 | Q60: 5 | S60: 1 | T60: 0 | U60: 0 | V60: =IF(OR(tickets_cleaned[[#This Row],[resolution_time_hours]]="", tickets_cleaned[[#This Row],[resolution_time_hours]]<0),"",tickets_cleaned[[#This Row],[resolution_time_hours]])
A61: 60 | B61: Samuel Schroeder | C61: andrew28@example.org | D61: 40 | E61: Other | F61: Apple AirPods | G61: 44444 | H61: Product inquiry | I61: Cancellation request | J61: I'm having an issue with the {product_purchased}. Please assist. Also note: Your information gets deleted every time an article is sent to a website you've never viewed. {Product_id} is a unique identifier in I'm not sure if this issue is specific to my device or if others have reported similar problems. | K61: Closed | L61: Reveal long fish care value direction TV. | M61: Medium | N61: Chat | O61: 45078.827 | P61: 45078.027 | Q61: 3 | S61: 1 | T61: 0 | U61: 0 | V61: =IF(OR(tickets_cleaned[[#This Row],[resolution_time_hours]]="", tickets_cleaned[[#This Row],[resolution_time_hours]]<0),"",tickets_cleaned[[#This Row],[resolution_time_hours]])
A62: 61 | B62: Amanda Burton | C62: hannahstephens@example.com | D62: 40 | E62: Male | F62: Sony 4K HDR TV | G62: 44151 | H62: Cancellation request | I62: Product setup | J62: I'm having an issue with the {product_purchased}. Please assist. It's time for me to update the product list I'm having an issue with the{product_purchased}. Please assist. It's time for I've performed a factory reset on my {product_purchased}, hoping it would resolve the problem, but it didn't help. | K62: Closed | L62: Else personal leg break book nearly. | M62: Medium | N62: Chat | O62: 45078.012 | P62: 45078.497 | Q62: 1 | R62: 11 | S62: 1 | T62: 0 | U62: 1 | V62: =IF(OR(tickets_cleaned[[#This Row],[resolution_time_hours]]="", tickets_cleaned[[#This Row],[resolution_time_hours]]<0),"",tickets_cleaned[[#This Row],[resolution_time_hours]]) -> 11
A63: 62 | B63: Sarah Williams | C63: akelly@example.net | D63: 41 | E63: Other | F63: Lenovo ThinkPad | G63: 44521 | H63: Product inquiry | I63: Battery life | J63: I'm having an issue with the {product_purchased}. Please assist. I was able to get my $50 bag from the vendor, but the bags I was wearing in the show were covered in stickers and the price for those I've tried different settings and configurations on my {product_purchased}, but the issue persists. | K63: Pending Customer Response | M63: Critical | N63: Social media | O63: 45078.064 | S63: 0 | T63: 1 | U63: 0 | V63: =IF(OR(tickets_cleaned[[#This Row],[resolution_time_hours]]="", tickets_cleaned[[#This Row],[resolution_time_hours]]<0),"",tickets_cleaned[[#This Row],[resolution_time_hours]])
A64: 63 | B64: Frank Sherman | C64: floresbryan@example.net | D64: 64 | E64: Female | F64: Xbox | G64: 44177 | H64: Billing inquiry | I64: Payment issue | J64: I'm having an issue with the {product_purchased}. Please assist. } } } function getProductCount () {orters(function ($p ) { // This gets the count for all the items in the The issue I'm facing is intermittent. Sometimes it works fine, but other times it acts up unexpectedly. | K64: Closed | L64: Eye while if exist name receive. | M64: High | N64: Email | O64: 45077.984 | P64: 45078.529 | Q64: 4 | R64: 13 | S64: 1 | T64: 0 | U64: 0 | V64: =IF(OR(tickets_cleaned[[#This Row],[resolution_time_hours]]="", tickets_cleaned[[#This Row],[resolution_time_hours]]<0),"",tickets_cleaned[[#This Row],[resolution_time_hours]]) -> 13
A65: 64 | B65: Victoria Parker | C65: tiffany87@example.com | D65: 57 | E65: Female | F65: Adobe Photoshop | G65: 43945 | H65: Billing inquiry | I65: Hardware issue | J65: I'm having an issue with the {product_purchased}. Please assist. 4.1.7 Add a custom app icon to the app window. Click App Manager. You'll see a list of all of the new apps ( I've checked the device settings and made sure that everything is configured correctly. | K65: Pending Customer Response | M65: High | N65: Phone | O65: 45078.297 | S65: 0 | T65: 1 | U65: 0 | V65: =IF(OR(tickets_cleaned[[#This Row],[resolution_time_hours]]="", tickets_cleaned[[#This Row],[resolution_time_hours]]<0),"",tickets_cleaned[[#This Row],[resolution_time_hours]])
A66: 65 | B66: David Smith | C66: jacob67@example.net | D66: 61 | E66: Male | F66: Microsoft Xbox Controller | G66: 44410 | H66: Technical issue | I66: Product compatibility | J66: I'm facing a problem with my {product_purchased}. The {product_purchased} is not turning on. It was working fine until yesterday, but now it doesn't respond. I'm working around this problem by switching off I've noticed a peculiar error message popping up on my {product_purchased} screen. It says '{error_message}'. What does it mean? | K66: Open | M66: Medium | N66: Phone | S66: 0 | T66: 1 | U66: 0 | V66: =IF(OR(tickets_cleaned[[#This Row],[resolution_time_hours]]="", tickets_cleaned[[#This Row],[resolution_time_hours]]<0),"",tickets_cleaned[[#This Row],[resolution_time_hours]])
A67: 66 | B67: Jeffrey Hernandez | C67: perezdana@example.org | D67: 56 | E67: Male | F67: Apple AirPods | G67: 44511 | H67: Technical issue | I67: Battery life | J67: There seems to be a glitch in the {product_purchased} software. It freezes frequently, making it difficult to use. Can you please provide a solution? "I'd love to do this on my own. It's a I've noticed a peculiar error message popping up on my {product_purchased} screen. It says '{error_message}'. What does it mean? | K67: Pending Customer Response | M67: Medium | N67: Phone | O67: 45077.943 | S67: 0 | T67: 1 | U67: 0 | V67: =IF(OR(tickets_cleaned[[#This Row],[resolution_time_hours]]="", tickets_cleaned[[#This Row],[resolution_time_hours]]<0),"",tickets_cleaned[[#This Row],[resolution_time_hours]])
A68: 67 | B68: John Robertson | C68: gillespiegeorge@example.com | D68: 49 | E68: Female | F68: GoPro Hero | G68: 44416 | H68: Billing inquiry | I68: Product compatibility | J68: I've noticed a software bug in the {product_purchased} app. It's causing data loss and unexpected errors. How can I resolve this issue? A good way to resolve this software issue is to use a custom configuration file The issue I'm facing is intermittent. Sometimes it works fine, but other times it acts up unexpectedly. | K68: Closed | L68: Fill young add between morning commercial. | M68: High | N68: Email | O68: 45078.213 | P68: 45078.429 | Q68: 5 | R68: 5 | S68: 1 | T68: 0 | U68: 0 | V68: =IF(OR(tickets_cleaned[[#This Row],[resolution_time_hours]]="", tickets_cleaned[[#This Row],[resolution_time_hours]]<0),"",tickets_cleaned[[#This Row],[resolution_time_hours]]) -> 5
A69: 68 | B69: Ryan Gonzalez | C69: pwilson@example.com | D69: 54 | E69: Male | F69: Microsoft Office | G69: 44374 | H69: Cancellation request | I69: Peripheral compatibility | J69: I've accidentally deleted important data from my {product_purchased}. Is there any way to recover the deleted files? I need them urgently. What can I do to recover them? Product purchases are never recoverable from the database. I'm worried that the issue might be hardware-related and might require repair or replacement. | K69: Pending Customer Response | M69: Low | N69: Phone | O69: 45078.878 | S69: 0 | T69: 1 | U69: 0 | V69: =IF(OR(tickets_cleaned[[#This Row],[resolution_time_hours]]="", tickets_cleaned[[#This Row],[resolution_time_hours]]<0),"",tickets_cleaned[[#This Row],[resolution_time_hours]])
A70: 69 | B70: Brianna Scott MD | C70: jbranch@example.net | D70: 51 | E70: Other | F70: Adobe Photoshop | G70: 44233 | H70: Technical issue | I70: Product compatibility | J70: I'm having an issue with the {product_purchased}. Please assist. If your product is purchased with the {product_purchased}, the {product_purchased} will be refunded. 7) Pay it I've performed a factory reset on my {product_purchased}, hoping it would resolve the problem, but it didn't help. | K70: Pending Customer Response | M70: Critical | N70: Chat | O70: 45077.958 | S70: 0 | T70: 1 | U70: 0 | V70: =IF(OR(tickets_cleaned[[#This Row],[resolution_time_hours]]="", tickets_cleaned[[#This Row],[resolution_time_hours]]<0),"",tickets_cleaned[[#This Row],[resolution_time_hours]])
A71: 70 | B71: Michael Day | C71: william07@example.org | D71: 46 | E71: Female | F71: Canon DSLR Camera | G71: 43874 | H71: Refund request | I71: Refund request | J71: I'm unable to access my {product_purchased} account. It keeps displaying an 'Invalid Credentials' error, even though I'm using the correct login information. How can I regain access to my account? If you don't I'm concerned about the security of my {product_purchased} and would like to ensure that my data is safe. | K71: Closed | L71: Answer story series imagine discover. | M71: High | N71: Chat | O71: 45078.498 | P71: 45077.952 | Q71: 1 | S71: 1 | T71: 0 | U71: 1 | V71: =IF(OR(tickets_cleaned[[#This Row],[resolution_time_hours]]="", tickets_cleaned[[#This Row],[resolution_time_hours]]<0),"",tickets_cleaned[[#This Row],[resolution_time_hours]])
A72: 71 | B72: Eileen Kim | C72: gabriel83@example.com | D72: 27 | E72: Male | F72: Google Pixel | G72: 44331 | H72: Cancellation request | I72: Product setup | J72: I've accidentally deleted important data from my {product_purchased}. Is there any way to recover the deleted files? I need them urgently. What about my {search } files? The {product_purchased} is the I'm using the original charger that came with my {product_purchased}, but it's not charging properly. | K72: Pending Customer Response | M72: Medium | N72: Chat | O72: 45077.993 | S72: 0 | T72: 1 | U72: 0 | V72: =IF(OR(tickets_cleaned[[#This Row],[resolution_time_hours]]="", tickets_cleaned[[#This Row],[resolution_time_hours]]<0),"",tickets_cleaned[[#This Row],[resolution_time_hours]])
A73: 72 | B73: Joseph Costa | C73: calvarez@example.org | D73: 37 | E73: Other | F73: iPhone | G73: 44100 | H73: Refund request | I73: Delivery problem | J73: I've recently set up my {product_purchased}, but it fails to connect to any available networks. What steps should I take to troubleshoot this issue? I've tried clearing the cache and data for the {product_purchased} app, but the issue persists. | K73: Open | M73: Medium | N73: Social media | S73: 0 | T73: 1 | U73: 0 | V73: =IF(OR(tickets_cleaned[[#This Row],[resolution_time_hours]]="", tickets_cleaned[[#This Row],[resolution_time_hours]]<0),"",tickets_cleaned[[#This Row],[resolution_time_hours]])
A74: 73 | B74: Tanya Powell | C74: epatel@example.org | D74: 34 | E74: Female | F74: Dyson Vacuum Cleaner | G74: 44243 | H74: Billing inquiry | I74: Display issue | J74: I'm having an issue with the {product_purchased}. Please assist. When I first noticed {product_purchased} the new price of the book was too high. I've already sent out the refund request, but they will I've checked for software updates, and my {product_purchased} is already running the latest version. | K74: Closed | L74: Executive wear gun child. | M74: Low | N74: Chat | O74: 45078.191 | P74: 45078.137 | Q74: 4 | S74: 1 | T74: 0 | U74: 0 | V74: =IF(OR(tickets_cleaned[[#This Row],[resolution_time_hours]]="", tickets_cleaned[[#This Row],[resolution_time_hours]]<0),"",tickets_cleaned[[#This Row],[resolution_time_hours]])
A75: 74 | B75: Philip Davis | C75: fbenjamin@example.org | D75: 36 | E75: Other | F75: Fitbit Charge | G75: 44144 | H75: Cancellation request | I75: Payment issue | J75: My {product_purchased} is making strange noises and not functioning properly. I suspect there might be a hardware issue. Can you please help me with this? This is a product that must fit in a box. Please let me I've noticed a peculiar error message popping up on my {product_purchased} screen. It says '{error_message}'. What does it mean? | K75: Closed | L75: Finish common benefit most college. | M75: Critical | N75: Social media | O75: 45078.897 | P75: 45078.1 | Q75: 3 | S75: 1 | T75: 0 | U75: 0 | V75: =IF(OR(tickets_cleaned[[#This Row],[resolution_time_hours]]="", tickets_cleaned[[#This Row],[resolution_time_hours]]<0),"",tickets_cleaned[[#This Row],[resolution_time_hours]])
A76: 75 | B76: Vanessa Hayes | C76: donaldroberts@example.net | D76: 31 | E76: Female | F76: Xbox | G76: 44302 | H76: Billing inquiry | I76: Product setup | J76: I'm having an issue with the {product_purchased}. Please assist. Please, take care of such requests. [1] M.V.V. [2] The above-mentioned is made up with specific I've checked the device settings and made sure that everything is configured correctly. | K76: Open | M76: Critical | N76: Email | S76: 0 | T76: 1 | U76: 0 | V76: =IF(OR(tickets_cleaned[[#This Row],[resolution_time_hours]]="", tickets_cleaned[[#This Row],[resolution_time_hours]]<0),"",tickets_cleaned[[#This Row],[resolution_time_hours]])
A77: 76 | B77: Jennifer Bryan | C77: cooperthomas@example.com | D77: 37 | E77: Other | F77: Roomba Robot Vacuum | G77: 44202 | H77: Product inquiry | I77: Display issue | J77: I'm having an issue with the {product_purchased}. Please assist. 1. It is not allowed to purchase a product from an individual, or for a company in which there are no specific employees or employees, and all products have to I've followed the troubleshooting steps mentioned in the user manual, but the issue persists. | K77: Closed | L77: Somebody east painting tree sell rock level. | M77: Critical | N77: Chat | O77: 45078.613 | P77: 45078.104 | Q77: 1 | S77: 1 | T77: 0 | U77: 1 | V77: =IF(OR(tickets_cleaned[[#This Row],[resolution_time_hours]]="", tickets_cleaned[[#This Row],[resolution_time_hours]]<0),"",tickets_cleaned[[#This Row],[resolution_time_hours]])
A78: 77 | B78: Matthew Scott | C78: brookeross@example.net | D78: 18 | E78: Other | F78: iPhone | G78: 44012 | H78: Cancellation request | I78: Account access | J78: I'm having an issue with the {product_purchased}. Please assist. I've got a customer who has sent me a $25 invoice! I want to know if this will correct this. I just downloaded the demo and I I'm experiencing this issue on multiple devices of the same model, so it seems to be a widespread problem. | K78: Open | M78: Critical | N78: Phone | S78: 0 | T78: 1 | U78: 0 | V78: =IF(OR(tickets_cleaned[[#This Row],[resolution_time_hours]]="", tickets_cleaned[[#This Row],[resolution_time_hours]]<0),"",tickets_cleaned[[#This Row],[resolution_time_hours]])
A79: 78 | B79: Alfred Ortiz | C79: nicholsdouglas@example.org | D79: 63 | E79: Female | F79: Fitbit Charge | G79: 44194 | H79: Billing inquiry | I79: Delivery problem | J79: I'm having an issue with the {product_purchased}. Please assist. Product #8 4-8-0-1 The product code on your product. #Product ID : {product_id I've checked the device settings and made sure that everything is configured correctly. | K79: Closed | L79: Huge value apply born. | M79: Low | N79: Email | O79: 45078.803 | P79: 45078.64 | Q79: 5 | S79: 1 | T79: 0 | U79: 0 | V79: =IF(OR(tickets_cleaned[[#This Row],[resolution_time_hours]]="", tickets_cleaned[[#This Row],[resolution_time_hours]]<0),"",tickets_cleaned[[#This Row],[resolution_time_hours]])
A80: 79 | B80: John Goodman | C80: vgarcia@example.com | D80: 55 | E80: Other | F80: Google Pixel | G80: 44203 | H80: Billing inquiry | I80: Data loss | J80: I'm having an issue with the {product_purchased}. Please assist. Thank you The customer's rating and reviews are important, but they don't have an impact on your credit score For over mogul financial companies who have I've performed a factory reset on my {product_purchased}, hoping it would resolve the problem, but it didn't help. | K80: Pending Customer Response | M80: Medium | N80: Social media | O80: 45078.707 | S80: 0 | T80: 1 | U80: 0 | V80: =IF(OR(tickets_cleaned[[#This Row],[resolution_time_hours]]="", tickets_cleaned[[#This Row],[resolution_time_hours]]<0),"",tickets_cleaned[[#This Row],[resolution_time_hours]])
A81: 80 | B81: Catherine Stephens | C81: hmccann@example.com | D81: 40 | E81: Other | F81: LG Smart TV | G81: 44138 | H81: Technical issue | I81: Software bug | J81: I'm having an issue with the {product_purchased}. Please assist. This is for the best experience and you can't use your phone while waiting for deliveries or when you pick it up. Please help by posting a I've tried using different cables, adapters, or peripherals with my {product_purchased}, but the issue persists. | K81: Pending Customer Response | M81: Critical | N81: Chat | O81: 45078.477 | S81: 0 | T81: 1 | U81: 0 | V81: =IF(OR(tickets_cleaned[[#This Row],[resolution_time_hours]]="", tickets_cleaned[[#This Row],[resolution_time_hours]]<0),"",tickets_cleaned[[#This Row],[resolution_time_hours]])
A82: 81 | B82: Sarah Lee | C82: dclark@example.net | D82: 50 | E82: Other | F82: Microsoft Office | G82: 44277 | H82: Technical issue | I82: Product recommendation | J82: I'm having an issue with the {product_purchased}. Please assist. I'm unable to find the option to perform the desired action in the {product_purchased}. Could you please guide me through the steps? | K82: Pending Customer Response | M82: Critical | N82: Phone | O82: 45078.311 | S82: 0 | T82: 1 | U82: 0 | V82: =IF(OR(tickets_cleaned[[#This Row],[resolution_time_hours]]="", tickets_cleaned[[#This Row],[resolution_time_hours]]<0),"",tickets_cleaned[[#This Row],[resolution_time_hours]])
A83: 82 | B83: Kiara Parker | C83: gonzalezlarry@example.org | D83: 29 | E83: Other | F83: Apple AirPods | G83: 44399 | H83: Cancellation request | I83: Cancellation request | J83: I'm encountering a software bug in the {product_purchased}. Whenever I try to perform a specific action, the application crashes. Are there any updates or fixes available? I don't know about any updates to the product. It's hard I'm unable to find the option to perform the desired action in the {product_purchased}. Could you please guide me through the steps? | K83: Pending Customer Response | M83: Medium | N83: Email | O83: 45078.484 | S83: 0 | T83: 1 | U83: 0 | V83: =IF(OR(tickets_cleaned[[#This Row],[resolution_time_hours]]="", tickets_cleaned[[#This Row],[resolution_time_hours]]<0),"",tickets_cleaned[[#This Row],[resolution_time_hours]])
A84: 83 | B84: Joshua Miller | C84: kimjesse@example.com | D84: 24 | E84: Male | F84: PlayStation | G84: 44473 | H84: Refund request | I84: Software bug | J84: I'm having an issue with the {product_purchased}. Please assist. <p> A full time customer service representative will arrive soon. <p> If you would like to respond to a message I've tried different settings and configurations on my {product_purchased}, but the issue persists. | K84: Closed | L84: Event see dinner home. | M84: Low | N84: Social media | O84: 45078.236 | P84: 45078.858 | Q84: 1 | R84: 14 | S84: 1 | T84: 0 | U84: 1 | V84: =IF(OR(tickets_cleaned[[#This Row],[resolution_time_hours]]="", tickets_cleaned[[#This Row],[resolution_time_hours]]<0),"",tickets_cleaned[[#This Row],[resolution_time_hours]]) -> 14
A85: 84 | B85: James Jones | C85: dsilva@example.org | D85: 57 | E85: Other | F85: Autodesk AutoCAD | G85: 44419 | H85: Technical issue | I85: Installation support | J85: I'm having an issue with the {product_purchased}. Please assist. Your product may be available on other websites with the same keyword or your brand. Thank you. I've noticed a sudden decrease in battery life on my {product_purchased}. It used to last much longer. | K85: Pending Customer Response | M85: Critical | N85: Phone | O85: 45078.017 | S85: 0 | T85: 1 | U85: 0 | V85: =IF(OR(tickets_cleaned[[#This Row],[resolution_time_hours]]="", tickets_cleaned[[#This Row],[resolution_time_hours]]<0),"",tickets_cleaned[[#This Row],[resolution_time_hours]])
A86: 85 | B86: David Taylor | C86: kaylapham@example.com | D86: 67 | E86: Other | F86: Microsoft Surface | G86: 44410 | H86: Technical issue | I86: Hardware issue | J86: I'm facing issues logging into my {product_purchased} account. It says my account is locked. What should I do to unlock it? Please log into your login browser and check to see if the account has been locked. I'm experiencing this issue on multiple devices of the same model, so it seems to be a widespread problem. | K86: Open | M86: Medium | N86: Phone | S86: 0 | T86: 1 | U86: 0 | V86: =IF(OR(tickets_cleaned[[#This Row],[resolution_time_hours]]="", tickets_cleaned[[#This Row],[resolution_time_hours]]<0),"",tickets_cleaned[[#This Row],[resolution_time_hours]])
A87: 86 | B87: Richard Mullen | C87: cschmidt@example.com | D87: 67 | E87: Female | F87: Canon EOS | G87: 44218 | H87: Product inquiry | I87: Peripheral compatibility | J87: I've forgotten my password for my {product_purchased} account, and the password reset option is not working. How can I recover my account? If you have not used login tokens for the previous 12 months, the login token I've reviewed the troubleshooting steps on the official support website, but they didn't resolve the problem. | K87: Open | M87: High | N87: Social media | S87: 0 | T87: 1 | U87: 0 | V87: =IF(OR(tickets_cleaned[[#This Row],[resolution_time_hours]]="", tickets_cleaned[[#This Row],[resolution_time_hours]]<0),"",tickets_cleaned[[#This Row],[resolution_time_hours]])
A88: 87 | B88: Danielle Everett | C88: kimberlyhudson@example.com | D88: 46 | E88: Male | F88: Sony PlayStation | G88: 43848 | H88: Technical issue | I88: Product recommendation | J88: I'm having an issue with the {product_purchased}. Please assist. * * * @param {number}_item * * @return {item} @*/if (_ejection_exceeds(_proposal)) I've noticed that the issue occurs consistently when I use a specific feature or application on my {product_purchased}. | K88: Closed | L88: Represent where produce suddenly. | M88: Critical | N88: Phone | O88: 45078.752 | P88: 45078.266 | Q88: 2 | S88: 1 | T88: 0 | U88: 1 | V88: =IF(OR(tickets_cleaned[[#This Row],[resolution_time_hours]]="", tickets_cleaned[[#This Row],[resolution_time_hours]]<0),"",tickets_cleaned[[#This Row],[resolution_time_hours]])
A89: 88 | B89: Steven Thompson | C89: vaustin@example.org | D89: 55 | E89: Other | F89: Philips Hue Lights | G89: 44084 | H89: Technical issue | I89: Delivery problem | J89: I'm facing a problem with my {product_purchased}. The {product_purchased} is not turning on. It was working fine until yesterday, but now it doesn't respond. I'm using a phone now, I'm unable to find the option to perform the desired action in the {product_purchased}. Could you please guide me through the steps? | K89: Pending Customer Response | M89: High | N89: Social media | O89: 45078.807 | S89: 0 | T89: 1 | U89: 0 | V89: =IF(OR(tickets_cleaned[[#This Row],[resolution_time_hours]]="", tickets_cleaned[[#This Row],[resolution_time_hours]]<0),"",tickets_cleaned[[#This Row],[resolution_time_hours]])
A90: 89 | B90: Renee White | C90: chelsea84@example.org | D90: 42 | E90: Other | F90: Nikon D | G90: 44409 | H90: Billing inquiry | I90: Product setup | J90: I'm having an issue with the {product_purchased}. Please assist. Product Purchasing Error Product Purchasing Error Yes | No 28 - 30 28 - 30 32 | Product Purchasing Error | Product Purchase Error I've reviewed the troubleshooting steps on the official support website, but they didn't resolve the problem. | K90: Open | M90: Critical | N90: Email | S90: 0 | T90: 1 | U90: 0 | V90: =IF(OR(tickets_cleaned[[#This Row],[resolution_time_hours]]="", tickets_cleaned[[#This Row],[resolution_time_hours]]<0),"",tickets_cleaned[[#This Row],[resolution_time_hours]])
A91: 90 | B91: Lisa Hill | C91: hinescarrie@example.org | D91: 40 | E91: Male | F91: Sony Xperia | G91: 43860 | H91: Product inquiry | I91: Product recommendation | J91: I'm having an issue with the {product_purchased}. Please assist. If your computer is connected to a power source, please do not open the {product_purchased}. Please assist. If your router is wired up I've already contacted customer support multiple times, but the issue remains unresolved. | K91: Closed | L91: Exactly red two dog. | M91: Medium | N91: Email | O91: 45077.971 | P91: 45078.132 | Q91: 5 | R91: 3 | S91: 1 | T91: 0 | U91: 0 | V91: =IF(OR(tickets_cleaned[[#This Row],[resolution_time_hours]]="", tickets_cleaned[[#This Row],[resolution_time_hours]]<0),"",tickets_cleaned[[#This Row],[resolution_time_hours]]) -> 3
A92: 91 | B92: Sandra Bass | C92: jamesbaxter@example.com | D92: 57 | E92: Other | F92: Sony Xperia | G92: 44119 | H92: Refund request | I92: Software bug | J92: I've forgotten my password for my {product_purchased} account, and the password reset option is not working. How can I recover my account? - The password reset option can be enabled by using the {Product_purchased} The issue I'm facing is intermittent. Sometimes it works fine, but other times it acts up unexpectedly. | K92: Pending Customer Response | M92: High | N92: Phone | O92: 45078.303 | S92: 0 | T92: 1 | U92: 0 | V92: =IF(OR(tickets_cleaned[[#This Row],[resolution_time_hours]]="", tickets_cleaned[[#This Row],[resolution_time_hours]]<0),"",tickets_cleaned[[#This Row],[resolution_time_hours]])
A93: 92 | B93: Madeline Osborne | C93: tyler12@example.net | D93: 62 | E93: Male | F93: iPhone | G93: 44514 | H93: Product inquiry | I93: Display issue | J93: I'm having an issue with the {product_purchased}. Please assist. (Beware when I accidentally add a link to your product and the item you selected incorrectly, you may see some data about missing items and it may require This problem started occurring after the recent software update. I haven't made any other changes to the device. | K93: Pending Customer Response | M93: Low | N93: Email | O93: 45078.01 | S93: 0 | T93: 1 | U93: 0 | V93: =IF(OR(tickets_cleaned[[#This Row],[resolution_time_hours]]="", tickets_cleaned[[#This Row],[resolution_time_hours]]<0),"",tickets_cleaned[[#This Row],[resolution_time_hours]])
A94: 93 | B94: Sydney Wagner | C94: paul73@example.com | D94: 44 | E94: Male | F94: Bose QuietComfort | G94: 44343 | H94: Technical issue | I94: Peripheral compatibility | J94: I'm having an issue with the {product_purchased}. Please assist. Here are some additional notes about using the product in order to purchase the product: The "new" name of the product is used. This name I've noticed a sudden decrease in battery life on my {product_purchased}. It used to last much longer. | K94: Pending Customer Response | M94: Low | N94: Email | O94: 45078.665 | S94: 0 | T94: 1 | U94: 0 | V94: =IF(OR(tickets_cleaned[[#This Row],[resolution_time_hours]]="", tickets_cleaned[[#This Row],[resolution_time_hours]]<0),"",tickets_cleaned[[#This Row],[resolution_time_hours]])
A95: 94 | B95: Jeremy Good | C95: michael25@example.net | D95: 32 | E95: Female | F95: PlayStation | G95: 44340 | H95: Refund request | I95: Installation support | J95: I'm having an issue with the {product_purchased}. Please assist. In-app purchases don't always match up with your new product. In-app purchases are very costly. Make sure you also check if your product is I've noticed a peculiar error message popping up on my {product_purchased} screen. It says '{error_message}'. What does it mean? | K95: Open | M95: Low | N95: Email | S95: 0 | T95: 1 | U95: 0 | V95: =IF(OR(tickets_cleaned[[#This Row],[resolution_time_hours]]="", tickets_cleaned[[#This Row],[resolution_time_hours]]<0),"",tickets_cleaned[[#This Row],[resolution_time_hours]])
A96: 95 | B96: Scott Estrada | C96: davidcox@example.org | D96: 65 | E96: Other | F96: Microsoft Xbox Controller | G96: 44536 | H96: Product inquiry | I96: Account access | J96: I'm having an issue with the {product_purchased}. Please assist. </name> <product_purchased_url >http://www.kyle@junebug.com/tutorial/cure-all- I've tried troubleshooting steps mentioned in the user manual, but the issue persists. | K96: Open | M96: Critical | N96: Phone | S96: 0 | T96: 1 | U96: 0 | V96: =IF(OR(tickets_cleaned[[#This Row],[resolution_time_hours]]="", tickets_cleaned[[#This Row],[resolution_time_hours]]<0),"",tickets_cleaned[[#This Row],[resolution_time_hours]])
A97: 96 | B97: Linda Campbell | C97: davisnatalie@example.net | D97: 60 | E97: Male | F97: Autodesk AutoCAD | G97: 44471 | H97: Product inquiry | I97: Battery life | J97: My {product_purchased} crashed, and I lost all the data stored on it. Is there any way to recover the lost data? Is there any way to recover the lost data? Can it be done remotely from a remote I've noticed a peculiar error message popping up on my {product_purchased} screen. It says '{error_message}'. What does it mean? | K97: Closed | L97: Series special into hour feel stuff. | M97: High | N97: Chat | O97: 45078.006 | P97: 45078.778 | Q97: 5 | R97: 18 | S97: 1 | T97: 0 | U97: 0 | V97: =IF(OR(tickets_cleaned[[#This Row],[resolution_time_hours]]="", tickets_cleaned[[#This Row],[resolution_time_hours]]<0),"",tickets_cleaned[[#This Row],[resolution_time_hours]]) -> 18
A98: 97 | B98: Charles Simpson | C98: vanessa39@example.net | D98: 18 | E98: Female | F98: Roomba Robot Vacuum | G98: 44129 | H98: Cancellation request | I98: Battery life | J98: I'm facing a problem with my {product_purchased}. The {product_purchased} is not turning on. It was working fine until yesterday, but now it doesn't respond. I'm thinking maybe they have a bug. I'm concerned about the security of my {product_purchased} and would like to ensure that my data is safe. | K98: Open | M98: High | N98: Social media | S98: 0 | T98: 1 | U98: 0 | V98: =IF(OR(tickets_cleaned[[#This Row],[resolution_time_hours]]="", tickets_cleaned[[#This Row],[resolution_time_hours]]<0),"",tickets_cleaned[[#This Row],[resolution_time_hours]])
A99: 98 | B99: Dan Newton | C99: deleonedward@example.net | D99: 22 | E99: Other | F99: Xbox | G99: 43848 | H99: Product inquiry | I99: Delivery problem | J99: I've recently set up my {product_purchased}, but it fails to connect to any available networks. What steps should I take to troubleshoot this issue? Step 1: You need to make sure that the DNS query you I've reviewed the troubleshooting steps on the official support website, but they didn't resolve the problem. | K99: Pending Customer Response | M99: High | N99: Email | O99: 45078.08 | S99: 0 | T99: 1 | U99: 0 | V99: =IF(OR(tickets_cleaned[[#This Row],[resolution_time_hours]]="", tickets_cleaned[[#This Row],[resolution_time_hours]]<0),"",tickets_cleaned[[#This Row],[resolution_time_hours]])
A100: 99 | B100: Nichole Huang | C100: sheryldawson@example.org | D100: 38 | E100: Male | F100: Samsung Galaxy | G100: 44083 | H100: Billing inquiry | I100: Refund request | J100: I'm having an issue with the {product_purchased}. Please assist. <s3> Please provide the product name, location and shipping address in the Product Overview. <s3> This message will be unread for 12 seconds. I've recently updated the firmware of my {product_purchased}, and the issue started happening afterward. Could it be related to the update? | K100: Closed | L100: Generation officer force test evening certain sign oil. | M100: High | N100: Chat | O100: 45078.296 | P100: 45078.615 | Q100: 5 | R100: 7 | S100: 1 | T100: 0 | U100: 0 | V100: =IF(OR(tickets_cleaned[[#This Row],[resolution_time_hours]]="", tickets_cleaned[[#This Row],[resolution_time_hours]]<0),"",tickets_cleaned[[#This Row],[resolution_time_hours]]) -> 7
...

Sheet KPI Summary
A1: metric_name | B1: metric_value
A2: total_tickets | B2: 8469
A3: closed_tickets | B3: 2769
A4: backlog_tickets | B4: 5700
A5: closed_ticket_rate_pct | B5: 32.7
A6: backlog_rate_pct | B6: 67.3
A7: avg_resolution_time_hours | B7: 7.11
A8: avg_csat_rating | B8: 2.99
A9: low_csat_rate_pct | B9: 39.8
A12: Total Tickets | C12: =TEXT(_xlfn.XLOOKUP("total_tickets",'KPI Summary'!$A:$A,'KPI Summary'!$B:$B,""),"#,##0") -> 8,469 | F12: Closed Tickets | H12: =TEXT(_xlfn.XLOOKUP("closed_tickets", 'KPI Summary'!$A:$A,'KPI Summary'!$B:$B),"#,##0") -> 2,769 | L12: Backog Tickets | N12: =TEXT(_xlfn.XLOOKUP("backlog_tickets", 'KPI Summary'!$A:$A,'KPI Summary'!$B:$B),"#,##0") -> 5,700 | Q12: Closed Rate | S12: =TEXT(_xlfn.XLOOKUP("closed_ticket_rate_pct", 'KPI Summary'!$A:$A,'KPI Summary'!$B:$B), "0.00")&"%" -> 32.70%
A16: Backlog Rate | C16: =TEXT(_xlfn.XLOOKUP("backlog_rate_pct",'KPI Summary'!$A:$A,'KPI Summary'!$B:$B), "0.00")&"%" -> 67.30% | F16: Avg CSAT | H16: =TEXT(_xlfn.XLOOKUP("avg_csat_rating", 'KPI Summary'!$A:$A,'KPI Summary'!$B:$B), "0.00")&"%" -> 2.99% | L16: Avg Resolution | N16: =TEXT(_xlfn.XLOOKUP("avg_resolution_time_hours", 'KPI Summary'!$A:$A,'KPI Summary'!$B:$B), "0.00")&"%" -> 7.11% | Q16: Low CSAT Rate | S16: =TEXT(_xlfn.XLOOKUP("low_csat_rate_pct",'KPI Summary'!$A:$A,'KPI Summary'!$B:$B), "0.00")&"%" -> 39.80%

Sheet By_Category
A1: ticket_type | B1: total_tickets | C1: closed_tickets | D1: closed_rate_pct
A2: Billing inquiry | B2: 1634 | C2: 544 | D2: 33.29
A3: Product inquiry | B3: 1641 | C3: 533 | D3: 32.48
A4: Cancellation request | B4: 1695 | C4: 516 | D4: 30.44
A5: Technical issue | B5: 1747 | C5: 580 | D5: 33.2
A6: Refund request | B6: 1752 | C6: 596 | D6: 34.02

Sheet By_Priority
A1: ticket_priority | B1: total_tickets | C1: backlog_tickets | D1: backlog_rate_pct
A2: Critical | B2: 2129 | C2: 1403 | D2: 65.9
A3: High | B3: 2085 | C3: 1380 | D3: 66.19
A4: Medium | B4: 2192 | C4: 1498 | D4: 68.34
A5: Low | B5: 2063 | C5: 1419 | D5: 68.78

Sheet By_Channel
A1: ticket_channel | B1: total_tickets | C1: closed_tickets | D1: avg_resolution_time_hours
A2: Email | B2: 2143 | C2: 720 | D2: 7.14
A3: Phone | B3: 2132 | C3: 691 | D3: 6.8
A4: Social media | B4: 2121 | C4: 684 | D4: 7.44
A5: Chat | B5: 2073 | C5: 674 | D5: 7.04

Sheet CSAT_Summary
A1: ticket_type | B1: rated_tickets | C1: avg_csat_rating | D1: low_csat_rate_pct
A2: Product inquiry | B2: 533 | C2: 3.02 | D2: 37.34
A3: Cancellation request | B3: 516 | C3: 3.03 | D3: 38.37
A4: Technical issue | B4: 580 | C4: 2.96 | D4: 40.34
A5: Billing inquiry | B5: 544 | C5: 3.03 | D5: 40.99
A6: Refund request | B6: 596 | C6: 2.93 | D6: 41.61

Sheet Monthly_Trend
A1: response_month | B1: total_tickets | C1: closed_tickets | D1: avg_csat_rating
A2: 45047 | B2: 175 | C2: 80 | D2: 3.04
A3: 45078 | B3: 5475 | C3: 2689 | D3: 2.99

Sheet Pivot tables
A1: KPIs
A3: Count of ticket_id | B3: Average of customer_satisfaction_rating | C3: Average of resolution_time_hours | D3: Average of Resolution_Time_Clean
A4: 8469 | B4: 2.9913326 | C4: 7.1096866 | D4: 7.1096866
A10: Count of ticket_id | B10: Sum of is_closed | C10: Resolution Rate (%) | D10: Backlog
A11: 8469 | B11: 2769 | C11: =GETPIVOTDATA("Sum of is_closed",$A$10)/GETPIVOTDATA("Count of ticket_id",$A$10) -> 0.32695714 | D11: =GETPIVOTDATA("Count of ticket_id",$A$10)-GETPIVOTDATA("Sum of is_closed",$A$10) -> 5700
A14: VOLUME
A15: Tickets per month
A16: Row Labels | B16: Count of ticket_id
A17: Jan | B17: 736
A18: Feb | B18: 715
A19: Mar | B19: 672
A20: Apr | B20: 718
A21: May | B21: 701
A22: Jun | B22: 678
A23: Jul | B23: 727
A24: Aug | B24: 691
A25: Sep | B25: 696
A26: Oct | B26: 735
A27: Nov | B27: 704
A28: Dec | B28: 696
A29: Grand Total | B29: 8469
A31: Tickets per status
A32: Row Labels | B32: Count of ticket_id
A33: Pending Customer Response | B33: 2881
A34: Open | B34: 2819
A35: Closed | B35: 2769
A36: Grand Total | B36: 8469
A48: PERFORMANCE
A49: Avg Resolution Time per month
A51: Row Labels | B51: Average of Resolution_Time_Clean
A52: May | B52: 0
A53: Jun | B53: 7.1198288
A54: Grand Total | B54: 7.1096866
A61: Resolution Time por Type
A62: Row Labels | B62: Average of Resolution_Time_Clean
A63: Billing inquiry | B63: 6.5494505
A64: Cancellation request | B64: 7.2264151
A65: Product inquiry | B65: 7.2256809
A66: Refund request | B66: 7.6315789
A67: Technical issue | B67: 6.8918033
A68: Grand Total | B68: 7.1096866
A74: Resolution Time por Priority
A75: Row Labels | B75: Average of Resolution_Time_Clean
A76: Critical | B76: 6.6497326
A77: High | B77: 7.6084507
A78: Low | B78: 7.494012
A79: Medium | B79: 6.7184751
A80: Grand Total | B80: 7.1096866
A92: CUSTOMER EXPERIENCE
A93: CSAT per month
A94: Row Labels | B94: Average of customer_satisfaction_rating
A95: May | B95: 2.8383838
A96: Jun | B96: 2.9970037
A97: Grand Total | B97: 2.9913326
A109: CSAT per Category
A110: Row Labels | B110: Tickets | C110: Avg CSAT
A111: Refund request | B111: 1752 | C111: 2.9345638
A112: Technical issue | B112: 1747 | C112: 2.9586207
A113: Product inquiry | B113: 1641 | C113: 3.0168856
A114: Billing inquiry | B114: 1634 | C114: 3.0275735
A115: Cancellation request | B115: 1695 | C115: 3.0290698
A116: Grand Total | B116: 8469 | C116: 2.9913326
A131: tickets_cleaned
A133: Tickets per Type
A134: Row Labels | B134: Count of ticket_id
A135: Billing inquiry | B135: 1634
A136: Product inquiry | B136: 1641
A137: Cancellation request | B137: 1695
A138: Technical issue | B138: 1747
A139: Refund request | B139: 1752
A140: Grand Total | B140: 8469
A148: Tickets per Priority
A149: Row Labels | B149: Count of ticket_id
A150: Low | B150: 2063
A151: High | B151: 2085
A152: Critical | B152: 2129
A153: Medium | B153: 2192
A154: Grand Total | B154: 8469
A164: Count of ticket_id | B164: Column Labels
A165: Row Labels | B165: Critical | C165: High | D165: Medium | E165: Low | F165: Grand Total
A166: Refund request | B166: 444 | C166: 448 | D166: 420 | E166: 440 | F166: 1752
A167: Technical issue | B167: 439 | C167: 458 | D167: 437 | E167: 413 | F167: 1747
A168: Cancellation request | B168: 423 | C168: 398 | D168: 460 | E168: 414 | F168: 1695
A169: Product inquiry | B169: 403 | C169: 399 | D169: 441 | E169: 398 | F169: 1641
A170: Billing inquiry | B170: 420 | C170: 382 | D170: 434 | E170: 398 | F170: 1634
A171: Grand Total | B171: 2129 | C171: 2085 | D171: 2192 | E171: 2063 | F171: 8469
A192: Sum of is_low_csat | B192: Count of customer_satisfaction_rating
A193: 1102 | B193: 2769 | D193: =GETPIVOTDATA("Sum of is_low_csat",$A$192) / GETPIVOTDATA("Count of customer_satisfaction_rating",$A$192) -> 0.39797761
A211: Row Labels | B211: Sum of metric_value
A212: avg_csat_rating | B212: 2.99
A213: avg_resolution_time_hours | B213: 7.11
A214: backlog_rate_pct | B214: 67.3
A215: backlog_tickets | B215: 5700
A216: closed_ticket_rate_pct | B216: 32.7
A217: closed_tickets | B217: 2769
A218: low_csat_rate_pct | B218: 39.8 | D218: =GETPIVOTDATA("metric_value",$A$211,"metric_name","low_csat_rate_pct") -> 39.8
A219: total_tickets | B219: 8469
A220: Grand Total | B220: 17087.9
